.gitignore
.readthedocs.yaml
LICENSE
MANIFEST.in
README.md
figure.png
pyproject.toml
.github/workflows/python-publish.yml
docs/Makefile
docs/abbrev_long.bib
docs/conf.py
docs/index.rst
docs/make.bat
docs/references.bib
docs/requirements.txt
docs/_static/styles/my_theme.css
docs/_templates/copyright.html
docs/_templates/autoapi/index.rst
docs/_templates/autoapi/python/attribute.rst
docs/_templates/autoapi/python/class.rst
docs/_templates/autoapi/python/data.rst
docs/_templates/autoapi/python/exception.rst
docs/_templates/autoapi/python/function.rst
docs/_templates/autoapi/python/method.rst
docs/_templates/autoapi/python/module.rst
docs/_templates/autoapi/python/package.rst
docs/_templates/autoapi/python/property.rst
src/barecat/__init__.py
src/barecat/_version.py
src/barecat/archive_formats.py
src/barecat/cli.py
src/barecat/cli_impl.py
src/barecat/codecs.py
src/barecat/common.py
src/barecat/consumed_threadpool.py
src/barecat/defrag.py
src/barecat/exceptions.py
src/barecat/from_tar_stream.py
src/barecat/glob_to_regex.py
src/barecat/progbar.py
src/barecat/threadsafe.py
src/barecat/to_tar_stream.py
src/barecat/upgrade_database.py
src/barecat/upgrade_database2.py
src/barecat/util.py
src/barecat/viewerqt6.py
src/barecat.egg-info/PKG-INFO
src/barecat.egg-info/SOURCES.txt
src/barecat.egg-info/dependency_links.txt
src/barecat.egg-info/entry_points.txt
src/barecat.egg-info/requires.txt
src/barecat.egg-info/top_level.txt
src/barecat/core/__init__.py
src/barecat/core/barecat.py
src/barecat/core/index.py
src/barecat/core/sharder.py
src/barecat/sql/schema.sql
tests/test_barecat.py
tests/test_cli.py