Metadata-Version: 2.4
Name: barecat
Version: 0.2.7
Summary: Scalable archive format for storing millions of small files with random access and SQLite indexing.
Author-email: István Sárándi <istvan.sarandi@gmail.com>
License: MIT License
Project-URL: Homepage, https://github.com/isarandi/barecat
Project-URL: Documentation, https://istvansarandi.com/docs/barecat/api/barecat/Barecat.html
Project-URL: Repository, https://github.com/isarandi/barecat
Project-URL: Issues, https://github.com/isarandi/barecat/issues
Project-URL: Author, https://istvansarandi.com
Keywords: sqlite,dataset,storage,archive,random-access,image-dataset,filesystem,key-value-store,deep-learning,data-loader,file-indexing
Classifier: Development Status :: 4 - Beta
Classifier: Intended Audience :: Developers
Classifier: Intended Audience :: Science/Research
Classifier: Topic :: Scientific/Engineering :: Information Analysis
Classifier: Topic :: Software Development :: Libraries
Classifier: Topic :: System :: Archiving
Classifier: Topic :: System :: Filesystems
Classifier: License :: OSI Approved :: MIT License
Classifier: Programming Language :: Python
Classifier: Programming Language :: Python :: 3
Classifier: Programming Language :: Cython
Classifier: Operating System :: POSIX :: Linux
Requires-Python: >=3.9
License-File: LICENSE
Requires-Dist: multiprocessing-utils
Requires-Dist: tqdm
Requires-Dist: crc32c
Dynamic: license-file
